haslda_log/__init__.py
haslda_log/log.py
haslda_log-0.0.2.dist-info/LICENSE
haslda_log-0.0.2.dist-info/METADATA
haslda_log-0.0.2.dist-info/WHEEL
haslda_log-0.0.2.dist-info/top_level.txt
haslda_log-0.0.2.dist-info/RECORD
