Metadata-Version: 2.1
Name: haslda-log
Version: 0.0.2
Summary: A simple logger
Author-email: David Haslwanter <dev@haslwanter.cc>
Classifier: Programming Language :: Python :: 3
Classifier: License :: OSI Approved :: MIT License
Classifier: Operating System :: OS Independent
License-File: LICENSE
